{
  "headline": "Stop Managing Software. Start Growing Customer Value.",
  "subtext": "SaveADay is a suite of 12+ AI-powered business apps that attract leads, convert bookings, nurture relationships, and reward loyalty — all working together, all manageable through a simple chat.",
  "badge": "Agentic CLV Platform",
  "valueProps": [
    {
      "label": "Attract",
      "emoji": "🧲",
      "text": "Capture leads, manage waitlists, and build audiences — without lifting a finger."
    },
    {
      "label": "Convert",
      "emoji": "📅",
      "text": "Turn enquiries into confirmed bookings and orders, instantly."
    },
    {
      "label": "Nurture",
      "emoji": "🤝",
      "text": "Stay in touch through updates, feedback, and personalised follow-ups."
    },
    {
      "label": "Retain",
      "emoji": "🎁",
      "text": "Reward loyalty and drive referrals so customers keep coming back."
    }
  ],
  "ctaPrimary": "Start Free",
  "ctaSecondary": "See How It Works"
}